word_frequency_analyzer/__init__.py
word_frequency_analyzer/__main__.py
word_frequency_analyzer/analyzer.py
word_frequency_analyzer-0.1.0.dist-info/licenses/LICENSE
word_frequency_analyzer-0.1.0.dist-info/METADATA
word_frequency_analyzer-0.1.0.dist-info/WHEEL
word_frequency_analyzer-0.1.0.dist-info/entry_points.txt
word_frequency_analyzer-0.1.0.dist-info/top_level.txt
word_frequency_analyzer-0.1.0.dist-info/RECORD
